Get_Password/__init__.py
Get_Password-0.0.1.dist-info/METADATA
Get_Password-0.0.1.dist-info/WHEEL
Get_Password-0.0.1.dist-info/top_level.txt
Get_Password-0.0.1.dist-info/RECORD
