Metadata-Version: 2.1
Name: Get-Password
Version: 0.0.1
Summary: Password_Generator
Author: tomedev
Author-email: sansion91@gmail.com
License: UNKNOWN
Platform: UNKNOWN
